urlToHTML/urltohtml.py
urlToHTML-1.0.0.dist-info/LICENSE
urlToHTML-1.0.0.dist-info/METADATA
urlToHTML-1.0.0.dist-info/WHEEL
urlToHTML-1.0.0.dist-info/top_level.txt
urlToHTML-1.0.0.dist-info/RECORD
