Metadata-Version: 2.1
Name: urlToHTML
Version: 1.0.0
Summary: Auto save HTML files from URLs for Offline Viewing
Home-page: https://github.com/Ronlin1/urlToHTML
Author: Ronnie Atuhaire
Author-email: ronlinx6@gmail.com
License: MIT
Keywords: HTML URLS Save Chrome Offline
Classifier: License :: OSI Approved :: MIT License
Classifier: Programming Language :: Python :: 3
Classifier: Programming Language :: Python :: 3.10
License-File: LICENSE
Requires-Dist: requests
